igwn_monitor/__init__.py
igwn_monitor/_version.py
igwn_monitor/auth.py
igwn_monitor/cli.py
igwn_monitor/compat.py
igwn_monitor/http.py
igwn_monitor/logging.py
igwn_monitor/sphinx.py
igwn_monitor/utils.py
igwn_monitor/plugins/__init__.py
igwn_monitor/plugins/check_command.py
igwn_monitor/plugins/check_cvmfs_age.py
igwn_monitor/plugins/check_data_availability.py
igwn_monitor/plugins/check_docdb.py
igwn_monitor/plugins/check_dqsegdb.py
igwn_monitor/plugins/check_dqsegdb_latency.py
igwn_monitor/plugins/check_file_latency.py
igwn_monitor/plugins/check_gettoken.py
igwn_monitor/plugins/check_gitlab.py
igwn_monitor/plugins/check_gracedb.py
igwn_monitor/plugins/check_grafana.py
igwn_monitor/plugins/check_gwdatafind.py
igwn_monitor/plugins/check_gwdatafind_latency.py
igwn_monitor/plugins/check_gwosc.py
igwn_monitor/plugins/check_htcondor.py
igwn_monitor/plugins/check_json.py
igwn_monitor/plugins/check_json_schema.json
igwn_monitor/plugins/check_kdc.py
igwn_monitor/plugins/check_kerberos_principal_expiry.py
igwn_monitor/plugins/check_koji.py
igwn_monitor/plugins/check_mattermost.py
igwn_monitor/plugins/check_nds2.py
igwn_monitor/plugins/check_nmap.py
igwn_monitor/plugins/check_partitions.py
igwn_monitor/plugins/check_pelican_latency.py
igwn_monitor/plugins/check_rsync.py
igwn_monitor/plugins/check_scitoken.py
igwn_monitor/plugins/check_scitoken_issuer.py
igwn_monitor/plugins/check_url.py
igwn_monitor/plugins/check_vault.py
igwn_monitor/plugins/check_vault_token.py
igwn_monitor/plugins/check_xrdcp.py
igwn_monitor/plugins/check_xrootd_latency.py
igwn_monitor/plugins/check_xrootd_ping.py
igwn_monitor/plugins/utils.py
igwn_monitor/tests/__init__.py
igwn_monitor/tests/test_auth.py
igwn_monitor/tests/test_http.py
igwn_monitor/tests/test_plugins.py
igwn_monitor/tests/test_sphinx.py
igwn_monitor/tests/test_utils.py
igwn_monitor/tests/plugins/__init__.py
igwn_monitor/tests/plugins/test_check_command.py
igwn_monitor/tests/plugins/test_check_cvmfs_age.py
igwn_monitor-1.3.1.dist-info/licenses/LICENSE
igwn_monitor-1.3.1.dist-info/METADATA
igwn_monitor-1.3.1.dist-info/WHEEL
igwn_monitor-1.3.1.dist-info/entry_points.txt
igwn_monitor-1.3.1.dist-info/top_level.txt
igwn_monitor-1.3.1.dist-info/RECORD
